GEOdb/__init__.py
GEOdb/common/__init__.py
GEOdb/common/configs.py
GEOdb/common/types.py
GEOdb/common/types_slim.py
GEOdb/common/web.py
GEOdb/parser/__init__.py
GEOdb/parser/series.py
GEOdb/scraper/__init__.py
GEOdb/scraper/main.py
GEOdb/scraper/sample_detail.py
GEOdb/scraper/series.py
GEOdb/scraper/series_detail.py
GEOdb/scraper/utils.py
geodb-0.2.0.1.dist-info/licenses/LICENSE
geodb-0.2.0.1.dist-info/METADATA
geodb-0.2.0.1.dist-info/WHEEL
geodb-0.2.0.1.dist-info/top_level.txt
geodb-0.2.0.1.dist-info/RECORD
