Metadata-Version: 2.4
Name: GEOdb
Version: 0.2.0.1
Summary: An asynchronous Python library for the Gene Expression Omnibus (GEO) database
Author-email: KumaTea <KumaTea@outlook.com>
Maintainer-email: KumaTea <KumaTea@outlook.com>
License-Expression: GPL-3.0-or-later
Project-URL: Homepage, https://github.com/KumaTea
Project-URL: Repository, https://github.com/KumaTea/GEOdb
Keywords: bioinformatics,gene-expression-omnibus
Classifier: Development Status :: 3 - Alpha
Classifier: Intended Audience :: Developers
Classifier: Programming Language :: Python
Classifier: Programming Language :: Python :: 3
Classifier: Programming Language :: Python :: 3.8
Classifier: Programming Language :: Python :: 3.9
Classifier: Programming Language :: Python :: 3.10
Classifier: Programming Language :: Python :: 3.11
Classifier: Programming Language :: Python :: 3.12
Classifier: Programming Language :: Python :: 3.13
Classifier: Programming Language :: Python :: Implementation
Classifier: Programming Language :: Python :: Implementation :: CPython
Classifier: Programming Language :: Python :: Implementation :: PyPy
Classifier: Topic :: Scientific/Engineering
Classifier: Topic :: Scientific/Engineering :: Bio-Informatics
Classifier: Topic :: Software Development :: Libraries
Classifier: Topic :: Software Development :: Libraries :: Python Modules
Requires-Python: >=3.8
License-File: LICENSE
Requires-Dist: aiohttp>=3.10.11
Requires-Dist: beautifulsoup4>=4.14.3
Requires-Dist: tqdm>=4.67.1
Dynamic: license-file
